vicdocs/__init__.py
vicdocs/vicdocs.py
vicdocs-0.0.1.dist-info/LICENSE
vicdocs-0.0.1.dist-info/METADATA
vicdocs-0.0.1.dist-info/WHEEL
vicdocs-0.0.1.dist-info/entry_points.txt
vicdocs-0.0.1.dist-info/top_level.txt
vicdocs-0.0.1.dist-info/RECORD
